[
  {
    "orderId": 1,
    "userId": 3,
    "items": [
      {
        "id": 1,
        "name": "Good Day Cashew Cookies",
        "quantity": 1,
        "unitSize": "200g",
        "itemsPerPack": 1,
        "note": ""
      },
      {
        "id": 2,
        "name": "Parle-G Gold Biscuits",
        "quantity": 1,
        "unitSize": "1kg",
        "itemsPerPack": 1,
        "note": ""
      },
      {
        "id": 6,
        "name": "Marie Gold Biscuits",
        "quantity": 1,
        "unitSize": "250g",
        "itemsPerPack": 1,
        "note": ""
      }
    ],
    "customerInfo": {
      "name": "Rashid",
      "mobile": "8290810250",
      "address": "test abc",
      "deliveryTime": "",
      "additionalNote": ""
    },
    "timestamp": "2025-07-28T15:35:47.814Z",
    "status": "pending"
  },
  {
    "orderId": 2,
    "userId": 3,
    "items": [
      {
        "id": 7,
        "name": "Monaco Salted Biscuits",
        "quantity": 2,
        "unitSize": "200g",
        "itemsPerPack": 1,
        "note": ""
      },
      {
        "id": 10,
        "name": "Kit Kat Chocolate",
        "quantity": 4,
        "unitSize": "37.3g",
        "itemsPerPack": 1,
        "note": ""
      }
    ],
    "customerInfo": {
      "name": "Rahul",
      "mobile": "8290810250",
      "address": "test abcd",
      "deliveryTime": "",
      "additionalNote": ""
    },
    "timestamp": "2025-07-28T15:41:21.806Z",
    "status": "pending"
  },
  {
    "orderId": 3,
    "userId": 3,
    "items": [
      {
        "id": 4,
        "name": "Ghari Detergent Powder",
        "quantity": 1,
        "unitSize": "1kg",
        "itemsPerPack": 1,
        "note": ""
      },
      {
        "id": 8,
        "name": "Kurkure Masala Munch",
        "quantity": 1,
        "unitSize": "100g",
        "itemsPerPack": 1,
        "note": ""
      },
      {
        "id": 12,
        "name": "Hide & Seek Chocolate Chips",
        "quantity": 1,
        "unitSize": "100g",
        "itemsPerPack": 1,
        "note": ""
      },
      {
        "id": 23,
        "name": "Boost Health Drink",
        "quantity": 1,
        "unitSize": "500g",
        "itemsPerPack": 1,
        "note": ""
      }
    ],
    "customerInfo": {
      "name": "Rahul",
      "mobile": "8290810250",
      "address": "test gfd",
      "deliveryTime": "",
      "additionalNote": ""
    },
    "timestamp": "2025-07-28T15:43:23.132Z",
    "status": "pending"
  }
]